pychromvar/__init__.py
pychromvar/compute_deviations.py
pychromvar/get_genome.py
pychromvar/match_motif.py
pychromvar/preprocessing.py
pychromvar-0.0.4.dist-info/LICENSE
pychromvar-0.0.4.dist-info/WHEEL
pychromvar-0.0.4.dist-info/METADATA
pychromvar-0.0.4.dist-info/RECORD
