Metadata-Version: 2.1
Name: pychromvar
Version: 0.0.4
Summary: A python package for chromVAR
Author-email: Zhijian Li <lzj1769@gmail.com>
Requires-Python: >= 3.8
Classifier: Programming Language :: Python :: 3
Classifier: License :: OSI Approved :: MIT License
Classifier: Operating System :: OS Independent
Classifier: Development Status :: 3 - Alpha
Classifier: Topic :: Scientific/Engineering :: Bio-Informatics
Classifier: Intended Audience :: Science/Research
Requires-Dist: scikit-learn
Requires-Dist: anndata
Requires-Dist: numpy
Requires-Dist: scipy
Requires-Dist: mudata
Requires-Dist: scanpy
Requires-Dist: muon
Requires-Dist: biopython
Requires-Dist: MOODS-python
Requires-Dist: pysam
Requires-Dist: wget
Project-URL: Documentation, https://pychromvar.readthedocs.io/en/latest/
Project-URL: Source, https://github.com/lzj1769/pychromVAR
